pySatlantic/__init__.py
pySatlantic/__main__.py
pySatlantic/dev.py
pySatlantic/instrument.py
pySatlantic/test.py
pySatlantic-0.4.2.dist-info/LICENSE
pySatlantic-0.4.2.dist-info/METADATA
pySatlantic-0.4.2.dist-info/WHEEL
pySatlantic-0.4.2.dist-info/top_level.txt
pySatlantic-0.4.2.dist-info/RECORD
