Metadata-Version: 2.1
Name: pySatlantic
Version: 0.4.2
Summary: Unpack binary messages from Satlantic instruments.
Home-page: https://github.com/OceanOptics/pySatlantic/
Author: Nils Haentjens
Author-email: nils.haentjens@maine.edu
License: MIT
Classifier: Programming Language :: Python :: 3
Classifier: License :: OSI Approved :: MIT License
Classifier: Operating System :: OS Independent
Classifier: Development Status :: 3 - Alpha
Classifier: Intended Audience :: Science/Research
Classifier: Intended Audience :: Education
Requires-Python: >=3.5
License-File: LICENSE
Requires-Dist: numpy
